{
    "total": [
        {
            "id": "100004684424730",
            "count": 0
        },
        {
            "id": "100010029484825",
            "count": 1
        },
        {
            "id": "100019801255841",
            "count": 1
        },
        {
            "id": "100022348665084",
            "count": 0
        },
        {
            "id": "100032983233886",
            "count": 0
        },
        {
            "id": "100039061186926",
            "count": 0
        },
        {
            "id": "100044878900409",
            "count": 23
        },
        {
            "id": "100048956991753",
            "count": 0
        },
        {
            "id": "100049159610595",
            "count": 10
        },
        {
            "id": "100051105343311",
            "count": 0
        },
        {
            "id": "100052994062977",
            "count": 0
        },
        {
            "id": "100054208005477",
            "count": 0
        },
        {
            "id": "100057536057742",
            "count": 0
        },
        {
            "id": "100062071786429",
            "count": 0
        },
        {
            "id": "100067364560128",
            "count": 0
        },
        {
            "id": "100067651526718",
            "count": 0
        },
        {
            "id": "100069923747843",
            "count": 0
        },
        {
            "id": "100073774891540",
            "count": 19
        },
        {
            "id": "100074525388507",
            "count": 0
        },
        {
            "id": "100074534096331",
            "count": 0
        },
        {
            "id": "100074842661648",
            "count": 1
        },
        {
            "id": "100075016774850",
            "count": 0
        },
        {
            "id": "100075185127964",
            "count": 0
        },
        {
            "id": "100075264987589",
            "count": 0
        },
        {
            "id": "100076391274701",
            "count": 4
        },
        {
            "id": "100077045706374",
            "count": 1
        },
        {
            "id": "100077129166126",
            "count": 0
        },
        {
            "id": "100077361785900",
            "count": 0
        },
        {
            "id": "100077375298014",
            "count": 0
        },
        {
            "id": "100077737358123",
            "count": 0
        },
        {
            "id": "100078925995229",
            "count": 0
        },
        {
            "id": "100080442044869",
            "count": 1
        },
        {
            "id": "100080471122818",
            "count": 64
        },
        {
            "id": "100080615717770",
            "count": 0
        },
        {
            "id": "100080669363101",
            "count": 5
        },
        {
            "id": "100080711966686",
            "count": 0
        },
        {
            "id": "100081083893557",
            "count": 1
        },
        {
            "id": "100081177011361",
            "count": 0
        },
        {
            "id": "100081756325592",
            "count": 0
        },
        {
            "id": "100082234253943",
            "count": 0
        },
        {
            "id": "100082342081896",
            "count": 10
        },
        {
            "id": "100082541624148",
            "count": 0
        },
        {
            "id": "100082757353124",
            "count": 0
        },
        {
            "id": "100083611688834",
            "count": 0
        },
        {
            "id": "100084163144826",
            "count": 3
        },
        {
            "id": "100084882070171",
            "count": 0
        },
        {
            "id": "100085095171446",
            "count": 1
        },
        {
            "id": "100085168684224",
            "count": 1
        },
        {
            "id": "100085208408068",
            "count": 0
        },
        {
            "id": "100085295070457",
            "count": 0
        },
        {
            "id": "100085564392261",
            "count": 0
        },
        {
            "id": "100085883055615",
            "count": 2
        },
        {
            "id": "100085900115447",
            "count": 6
        },
        {
            "id": "100085937242135",
            "count": 59
        },
        {
            "id": "100086290850267",
            "count": 0
        },
        {
            "id": "100086303567784",
            "count": 10
        },
        {
            "id": "100086338126407",
            "count": 0
        },
        {
            "id": "100086411966223",
            "count": 18
        },
        {
            "id": "100086479540822",
            "count": 0
        },
        {
            "id": "100086537319292",
            "count": 0
        },
        {
            "id": "100086608024718",
            "count": 0
        },
        {
            "id": "100087177684780",
            "count": 0
        },
        {
            "id": "100087223032350",
            "count": 0
        },
        {
            "id": "100087241632583",
            "count": 26
        },
        {
            "id": "100087403423132",
            "count": 0
        },
        {
            "id": "100087444015436",
            "count": 0
        },
        {
            "id": "100087446109575",
            "count": 0
        },
        {
            "id": "100087451973736",
            "count": 0
        },
        {
            "id": "100087452826273",
            "count": 0
        },
        {
            "id": "100087581193427",
            "count": 0
        },
        {
            "id": "100087661293189",
            "count": 0
        },
        {
            "id": "100087708564424",
            "count": 0
        },
        {
            "id": "100087728212545",
            "count": 3
        },
        {
            "id": "100087735655975",
            "count": 0
        },
        {
            "id": "100087788967099",
            "count": 0
        },
        {
            "id": "100088009904591",
            "count": 2
        },
        {
            "id": "100088080985247",
            "count": 0
        },
        {
            "id": "100088239654137",
            "count": 0
        },
        {
            "id": "100088304013841",
            "count": 0
        },
        {
            "id": "100088371745793",
            "count": 0
        },
        {
            "id": "100088396034616",
            "count": 1
        },
        {
            "id": "100088426704778",
            "count": 15
        },
        {
            "id": "100088454352569",
            "count": 0
        },
        {
            "id": "100088727191960",
            "count": 0
        },
        {
            "id": "100088736285141",
            "count": 0
        },
        {
            "id": "100088879443469",
            "count": 0
        },
        {
            "id": "100089006970460",
            "count": 0
        },
        {
            "id": "100089021537065",
            "count": 0
        },
        {
            "id": "100089037437822",
            "count": 2
        },
        {
            "id": "100089078937363",
            "count": 0
        },
        {
            "id": "100089135401934",
            "count": 6
        },
        {
            "id": "100089270354928",
            "count": 0
        },
        {
            "id": "100089311044327",
            "count": 0
        },
        {
            "id": "100089319577789",
            "count": 0
        },
        {
            "id": "100089594261658",
            "count": 0
        },
        {
            "id": "100089597169878",
            "count": 0
        },
        {
            "id": "100089608287247",
            "count": 0
        },
        {
            "id": "100089615088261",
            "count": 0
        },
        {
            "id": "100089752437202",
            "count": 0
        },
        {
            "id": "100089854377008",
            "count": 0
        },
        {
            "id": "100089892835963",
            "count": 0
        },
        {
            "id": "100089914403718",
            "count": 0
        },
        {
            "id": "100089918617197",
            "count": 2
        },
        {
            "id": "100089933977196",
            "count": 1
        },
        {
            "id": "100089948816816",
            "count": 2
        },
        {
            "id": "100090047276847",
            "count": 5
        },
        {
            "id": "100090075093924",
            "count": 5
        },
        {
            "id": "100090204715224",
            "count": 0
        },
        {
            "id": "100090206681674",
            "count": 0
        },
        {
            "id": "100090232310769",
            "count": 9
        },
        {
            "id": "100090287706395",
            "count": 0
        },
        {
            "id": "100090349088487",
            "count": 10
        },
        {
            "id": "100090480626218",
            "count": 0
        },
        {
            "id": "100090487747838",
            "count": 0
        },
        {
            "id": "100090573266947",
            "count": 0
        },
        {
            "id": "100090586627799",
            "count": 25
        },
        {
            "id": "100090667071803",
            "count": 0
        },
        {
            "id": "100090892813611",
            "count": 0
        },
        {
            "id": "100090931960391",
            "count": 0
        },
        {
            "id": "100091169177735",
            "count": 0
        },
        {
            "id": "100091242102045",
            "count": 0
        },
        {
            "id": "100091356849300",
            "count": 0
        },
        {
            "id": "100091364680112",
            "count": 0
        },
        {
            "id": "100091370330916",
            "count": 0
        },
        {
            "id": "100091393628777",
            "count": 0
        },
        {
            "id": "100091438323320",
            "count": 0
        },
        {
            "id": "100091472761117",
            "count": 0
        },
        {
            "id": "100091487242291",
            "count": 0
        },
        {
            "id": "100091694487260",
            "count": 0
        },
        {
            "id": "100092212964221",
            "count": 0
        },
        {
            "id": "100092213439559",
            "count": 0
        },
        {
            "id": "100092401010035",
            "count": 0
        },
        {
            "id": "100092729792306",
            "count": 2
        }
    ],
    "week": [
        {
            "id": "100004684424730",
            "count": 0,
            "name": "Người dùng facebook"
        },
        {
            "id": "100010029484825",
            "count": 1,
            "name": "Người dùng facebook"
        },
        {
            "id": "100019801255841",
            "count": 1,
            "name": "Người dùng facebook"
        },
        {
            "id": "100022348665084",
            "count": 0,
            "name": "Người dùng facebook"
        },
        {
            "id": "100032983233886",
            "count": 0,
            "name": "Người dùng facebook"
        },
        {
            "id": "100039061186926",
            "count": 0,
            "name": "Người dùng facebook"
        },
        {
            "id": "100044878900409",
            "count": 23,
            "name": "Người dùng facebook"
        },
        {
            "id": "100048956991753",
            "count": 0,
            "name": "Người dùng facebook"
        },
        {
            "id": "100049159610595",
            "count": 10,
            "name": "Người dùng facebook"
        },
        {
            "id": "100051105343311",
            "count": 0,
            "name": "Người dùng facebook"
        },
        {
            "id": "100052994062977",
            "count": 0,
            "name": "Người dùng facebook"
        },
        {
            "id": "100054208005477",
            "count": 0,
            "name": "Người dùng facebook"
        },
        {
            "id": "100057536057742",
            "count": 0,
            "name": "Người dùng facebook"
        },
        {
            "id": "100062071786429",
            "count": 0,
            "name": "Người dùng facebook"
        },
        {
            "id": "100067364560128",
            "count": 0,
            "name": "Người dùng facebook"
        },
        {
            "id": "100067651526718",
            "count": 0,
            "name": "Người dùng facebook"
        },
        {
            "id": "100069923747843",
            "count": 0,
            "name": "Người dùng facebook"
        },
        {
            "id": "100073774891540",
            "count": 19,
            "name": "Người dùng facebook"
        },
        {
            "id": "100074525388507",
            "count": 0,
            "name": "Người dùng facebook"
        },
        {
            "id": "100074534096331",
            "count": 0,
            "name": "Người dùng facebook"
        },
        {
            "id": "100074842661648",
            "count": 1,
            "name": "Người dùng facebook"
        },
        {
            "id": "100075016774850",
            "count": 0,
            "name": "Người dùng facebook"
        },
        {
            "id": "100075185127964",
            "count": 0,
            "name": "Người dùng facebook"
        },
        {
            "id": "100075264987589",
            "count": 0,
            "name": "Người dùng facebook"
        },
        {
            "id": "100076391274701",
            "count": 4,
            "name": "Người dùng facebook"
        },
        {
            "id": "100077045706374",
            "count": 1,
            "name": "Người dùng facebook"
        },
        {
            "id": "100077129166126",
            "count": 0,
            "name": "Người dùng facebook"
        },
        {
            "id": "100077361785900",
            "count": 0,
            "name": "Người dùng facebook"
        },
        {
            "id": "100077375298014",
            "count": 0,
            "name": "Người dùng facebook"
        },
        {
            "id": "100077737358123",
            "count": 0,
            "name": "Người dùng facebook"
        },
        {
            "id": "100078925995229",
            "count": 0,
            "name": "Người dùng facebook"
        },
        {
            "id": "100080442044869",
            "count": 1,
            "name": "Người dùng facebook"
        },
        {
            "id": "100080471122818",
            "count": 64,
            "name": "Người dùng facebook"
        },
        {
            "id": "100080615717770",
            "count": 0,
            "name": "Người dùng facebook"
        },
        {
            "id": "100080669363101",
            "count": 5,
            "name": "Người dùng facebook"
        },
        {
            "id": "100080711966686",
            "count": 0,
            "name": "Người dùng facebook"
        },
        {
            "id": "100081083893557",
            "count": 1,
            "name": "Người dùng facebook"
        },
        {
            "id": "100081177011361",
            "count": 0,
            "name": "Người dùng facebook"
        },
        {
            "id": "100081756325592",
            "count": 0,
            "name": "Người dùng facebook"
        },
        {
            "id": "100082234253943",
            "count": 0,
            "name": "Người dùng facebook"
        },
        {
            "id": "100082342081896",
            "count": 10,
            "name": "Người dùng facebook"
        },
        {
            "id": "100082541624148",
            "count": 0,
            "name": "Người dùng facebook"
        },
        {
            "id": "100082757353124",
            "count": 0,
            "name": "Người dùng facebook"
        },
        {
            "id": "100083611688834",
            "count": 0,
            "name": "Người dùng facebook"
        },
        {
            "id": "100084163144826",
            "count": 3,
            "name": "Người dùng facebook"
        },
        {
            "id": "100084882070171",
            "count": 0,
            "name": "Người dùng facebook"
        },
        {
            "id": "100085095171446",
            "count": 1,
            "name": "Người dùng facebook"
        },
        {
            "id": "100085168684224",
            "count": 1,
            "name": "Người dùng facebook"
        },
        {
            "id": "100085208408068",
            "count": 0,
            "name": "Người dùng facebook"
        },
        {
            "id": "100085295070457",
            "count": 0,
            "name": "Người dùng facebook"
        },
        {
            "id": "100085564392261",
            "count": 0,
            "name": "Người dùng facebook"
        },
        {
            "id": "100085883055615",
            "count": 2,
            "name": "Người dùng facebook"
        },
        {
            "id": "100085900115447",
            "count": 6,
            "name": "Người dùng facebook"
        },
        {
            "id": "100085937242135",
            "count": 59,
            "name": "Người dùng facebook"
        },
        {
            "id": "100086290850267",
            "count": 0,
            "name": "Người dùng facebook"
        },
        {
            "id": "100086303567784",
            "count": 10,
            "name": "Người dùng facebook"
        },
        {
            "id": "100086338126407",
            "count": 0,
            "name": "Người dùng facebook"
        },
        {
            "id": "100086411966223",
            "count": 18,
            "name": "Người dùng facebook"
        },
        {
            "id": "100086479540822",
            "count": 0,
            "name": "Người dùng facebook"
        },
        {
            "id": "100086537319292",
            "count": 0,
            "name": "Người dùng facebook"
        },
        {
            "id": "100086608024718",
            "count": 0,
            "name": "Người dùng facebook"
        },
        {
            "id": "100087177684780",
            "count": 0,
            "name": "Người dùng facebook"
        },
        {
            "id": "100087223032350",
            "count": 0,
            "name": "Người dùng facebook"
        },
        {
            "id": "100087241632583",
            "count": 26,
            "name": "Anya Bot"
        },
        {
            "id": "100087403423132",
            "count": 0,
            "name": "Người dùng facebook"
        },
        {
            "id": "100087444015436",
            "count": 0,
            "name": "Người dùng facebook"
        },
        {
            "id": "100087446109575",
            "count": 0,
            "name": "Người dùng facebook"
        },
        {
            "id": "100087451973736",
            "count": 0,
            "name": "Người dùng facebook"
        },
        {
            "id": "100087452826273",
            "count": 0,
            "name": "Người dùng facebook"
        },
        {
            "id": "100087581193427",
            "count": 0,
            "name": "Người dùng facebook"
        },
        {
            "id": "100087661293189",
            "count": 0,
            "name": "Người dùng facebook"
        },
        {
            "id": "100087708564424",
            "count": 0,
            "name": "Người dùng facebook"
        },
        {
            "id": "100087728212545",
            "count": 3,
            "name": "Người dùng facebook"
        },
        {
            "id": "100087735655975",
            "count": 0,
            "name": "Người dùng facebook"
        },
        {
            "id": "100087788967099",
            "count": 0,
            "name": "Người dùng facebook"
        },
        {
            "id": "100088009904591",
            "count": 2,
            "name": "Người dùng facebook"
        },
        {
            "id": "100088080985247",
            "count": 0,
            "name": "Người dùng facebook"
        },
        {
            "id": "100088239654137",
            "count": 0,
            "name": "Người dùng facebook"
        },
        {
            "id": "100088304013841",
            "count": 0,
            "name": "Người dùng facebook"
        },
        {
            "id": "100088371745793",
            "count": 0,
            "name": "Người dùng facebook"
        },
        {
            "id": "100088396034616",
            "count": 1,
            "name": "Người dùng facebook"
        },
        {
            "id": "100088426704778",
            "count": 15,
            "name": "Người dùng facebook"
        },
        {
            "id": "100088454352569",
            "count": 0,
            "name": "Người dùng facebook"
        },
        {
            "id": "100088727191960",
            "count": 0,
            "name": "Người dùng facebook"
        },
        {
            "id": "100088736285141",
            "count": 0,
            "name": "Người dùng facebook"
        },
        {
            "id": "100088879443469",
            "count": 0,
            "name": "Người dùng facebook"
        },
        {
            "id": "100089006970460",
            "count": 0,
            "name": "Người dùng facebook"
        },
        {
            "id": "100089021537065",
            "count": 0,
            "name": "Người dùng facebook"
        },
        {
            "id": "100089037437822",
            "count": 2,
            "name": "Người dùng facebook"
        },
        {
            "id": "100089078937363",
            "count": 0,
            "name": "Người dùng facebook"
        },
        {
            "id": "100089135401934",
            "count": 6,
            "name": "Người dùng facebook"
        },
        {
            "id": "100089270354928",
            "count": 0,
            "name": "Người dùng facebook"
        },
        {
            "id": "100089311044327",
            "count": 0,
            "name": "Người dùng facebook"
        },
        {
            "id": "100089319577789",
            "count": 0,
            "name": "Người dùng facebook"
        },
        {
            "id": "100089594261658",
            "count": 0,
            "name": "Người dùng facebook"
        },
        {
            "id": "100089597169878",
            "count": 0,
            "name": "Người dùng facebook"
        },
        {
            "id": "100089608287247",
            "count": 0,
            "name": "Người dùng facebook"
        },
        {
            "id": "100089615088261",
            "count": 0,
            "name": "Người dùng facebook"
        },
        {
            "id": "100089752437202",
            "count": 0,
            "name": "Người dùng facebook"
        },
        {
            "id": "100089854377008",
            "count": 0,
            "name": "Người dùng facebook"
        },
        {
            "id": "100089892835963",
            "count": 0,
            "name": "Người dùng facebook"
        },
        {
            "id": "100089914403718",
            "count": 0,
            "name": "Người dùng facebook"
        },
        {
            "id": "100089918617197",
            "count": 2,
            "name": "Người dùng facebook"
        },
        {
            "id": "100089933977196",
            "count": 1,
            "name": "Người dùng facebook"
        },
        {
            "id": "100089948816816",
            "count": 2,
            "name": "Người dùng facebook"
        },
        {
            "id": "100090047276847",
            "count": 5,
            "name": "Người dùng facebook"
        },
        {
            "id": "100090075093924",
            "count": 4,
            "name": "Tri Nity"
        },
        {
            "id": "100090204715224",
            "count": 0,
            "name": "Người dùng facebook"
        },
        {
            "id": "100090206681674",
            "count": 0,
            "name": "Người dùng facebook"
        },
        {
            "id": "100090232310769",
            "count": 9,
            "name": "Người dùng facebook"
        },
        {
            "id": "100090287706395",
            "count": 0,
            "name": "Người dùng facebook"
        },
        {
            "id": "100090349088487",
            "count": 10,
            "name": "Người dùng facebook"
        },
        {
            "id": "100090480626218",
            "count": 0,
            "name": "Người dùng facebook"
        },
        {
            "id": "100090487747838",
            "count": 0,
            "name": "Người dùng facebook"
        },
        {
            "id": "100090573266947",
            "count": 0,
            "name": "Người dùng facebook"
        },
        {
            "id": "100090586627799",
            "count": 25,
            "name": "Người dùng facebook"
        },
        {
            "id": "100090667071803",
            "count": 0,
            "name": "Người dùng facebook"
        },
        {
            "id": "100090892813611",
            "count": 0,
            "name": "Người dùng facebook"
        },
        {
            "id": "100090931960391",
            "count": 0,
            "name": "Người dùng facebook"
        },
        {
            "id": "100091169177735",
            "count": 0,
            "name": "Người dùng facebook"
        },
        {
            "id": "100091242102045",
            "count": 0,
            "name": "Người dùng facebook"
        },
        {
            "id": "100091356849300",
            "count": 0,
            "name": "Người dùng facebook"
        },
        {
            "id": "100091364680112",
            "count": 0,
            "name": "Người dùng facebook"
        },
        {
            "id": "100091370330916",
            "count": 0,
            "name": "Người dùng facebook"
        },
        {
            "id": "100091393628777",
            "count": 0,
            "name": "Người dùng facebook"
        },
        {
            "id": "100091438323320",
            "count": 0,
            "name": "Người dùng facebook"
        },
        {
            "id": "100091472761117",
            "count": 0,
            "name": "Người dùng facebook"
        },
        {
            "id": "100091487242291",
            "count": 0,
            "name": "Người dùng facebook"
        },
        {
            "id": "100091694487260",
            "count": 0,
            "name": "Người dùng facebook"
        },
        {
            "id": "100092212964221",
            "count": 0,
            "name": "Người dùng facebook"
        },
        {
            "id": "100092213439559",
            "count": 0,
            "name": "Người dùng facebook"
        },
        {
            "id": "100092401010035",
            "count": 0,
            "name": "Người dùng facebook"
        },
        {
            "id": "100092729792306",
            "count": 0,
            "name": "dave愛"
        }
    ],
    "day": [
        {
            "id": "100004684424730",
            "count": 0,
            "name": "Người dùng facebook"
        },
        {
            "id": "100010029484825",
            "count": 0,
            "name": "Người dùng facebook"
        },
        {
            "id": "100019801255841",
            "count": 0,
            "name": "Người dùng facebook"
        },
        {
            "id": "100022348665084",
            "count": 0,
            "name": "Người dùng facebook"
        },
        {
            "id": "100032983233886",
            "count": 0,
            "name": "Người dùng facebook"
        },
        {
            "id": "100039061186926",
            "count": 0,
            "name": "Người dùng facebook"
        },
        {
            "id": "100044878900409",
            "count": 0,
            "name": "Người dùng facebook"
        },
        {
            "id": "100048956991753",
            "count": 0,
            "name": "Người dùng facebook"
        },
        {
            "id": "100049159610595",
            "count": 0,
            "name": "Người dùng facebook"
        },
        {
            "id": "100051105343311",
            "count": 0,
            "name": "Người dùng facebook"
        },
        {
            "id": "100052994062977",
            "count": 0,
            "name": "Người dùng facebook"
        },
        {
            "id": "100054208005477",
            "count": 0,
            "name": "Người dùng facebook"
        },
        {
            "id": "100057536057742",
            "count": 0,
            "name": "Người dùng facebook"
        },
        {
            "id": "100062071786429",
            "count": 0,
            "name": "Người dùng facebook"
        },
        {
            "id": "100067364560128",
            "count": 0,
            "name": "Người dùng facebook"
        },
        {
            "id": "100067651526718",
            "count": 0,
            "name": "Người dùng facebook"
        },
        {
            "id": "100069923747843",
            "count": 0,
            "name": "Người dùng facebook"
        },
        {
            "id": "100073774891540",
            "count": 0,
            "name": "Người dùng facebook"
        },
        {
            "id": "100074525388507",
            "count": 0,
            "name": "Người dùng facebook"
        },
        {
            "id": "100074534096331",
            "count": 0,
            "name": "Người dùng facebook"
        },
        {
            "id": "100074842661648",
            "count": 0,
            "name": "Người dùng facebook"
        },
        {
            "id": "100075016774850",
            "count": 0,
            "name": "Người dùng facebook"
        },
        {
            "id": "100075185127964",
            "count": 0,
            "name": "Người dùng facebook"
        },
        {
            "id": "100075264987589",
            "count": 0,
            "name": "Người dùng facebook"
        },
        {
            "id": "100076391274701",
            "count": 0,
            "name": "Người dùng facebook"
        },
        {
            "id": "100077045706374",
            "count": 0,
            "name": "Người dùng facebook"
        },
        {
            "id": "100077129166126",
            "count": 0,
            "name": "Người dùng facebook"
        },
        {
            "id": "100077361785900",
            "count": 0,
            "name": "Người dùng facebook"
        },
        {
            "id": "100077375298014",
            "count": 0,
            "name": "Người dùng facebook"
        },
        {
            "id": "100077737358123",
            "count": 0,
            "name": "Người dùng facebook"
        },
        {
            "id": "100078925995229",
            "count": 0,
            "name": "Người dùng facebook"
        },
        {
            "id": "100080442044869",
            "count": 0,
            "name": "Người dùng facebook"
        },
        {
            "id": "100080471122818",
            "count": 0,
            "name": "Người dùng facebook"
        },
        {
            "id": "100080615717770",
            "count": 0,
            "name": "Người dùng facebook"
        },
        {
            "id": "100080669363101",
            "count": 0,
            "name": "Người dùng facebook"
        },
        {
            "id": "100080711966686",
            "count": 0,
            "name": "Người dùng facebook"
        },
        {
            "id": "100081083893557",
            "count": 0,
            "name": "Người dùng facebook"
        },
        {
            "id": "100081177011361",
            "count": 0,
            "name": "Người dùng facebook"
        },
        {
            "id": "100081756325592",
            "count": 0,
            "name": "Người dùng facebook"
        },
        {
            "id": "100082234253943",
            "count": 0,
            "name": "Người dùng facebook"
        },
        {
            "id": "100082342081896",
            "count": 0,
            "name": "Người dùng facebook"
        },
        {
            "id": "100082541624148",
            "count": 0,
            "name": "Người dùng facebook"
        },
        {
            "id": "100082757353124",
            "count": 0,
            "name": "Người dùng facebook"
        },
        {
            "id": "100083611688834",
            "count": 0,
            "name": "Người dùng facebook"
        },
        {
            "id": "100084163144826",
            "count": 0,
            "name": "Người dùng facebook"
        },
        {
            "id": "100084882070171",
            "count": 0,
            "name": "Người dùng facebook"
        },
        {
            "id": "100085095171446",
            "count": 0,
            "name": "Người dùng facebook"
        },
        {
            "id": "100085168684224",
            "count": 0,
            "name": "Người dùng facebook"
        },
        {
            "id": "100085208408068",
            "count": 0,
            "name": "Người dùng facebook"
        },
        {
            "id": "100085295070457",
            "count": 0,
            "name": "Người dùng facebook"
        },
        {
            "id": "100085564392261",
            "count": 0,
            "name": "Người dùng facebook"
        },
        {
            "id": "100085883055615",
            "count": 0,
            "name": "Người dùng facebook"
        },
        {
            "id": "100085900115447",
            "count": 0,
            "name": "Người dùng facebook"
        },
        {
            "id": "100085937242135",
            "count": 0,
            "name": "Người dùng facebook"
        },
        {
            "id": "100086290850267",
            "count": 0,
            "name": "Người dùng facebook"
        },
        {
            "id": "100086303567784",
            "count": 0,
            "name": "Người dùng facebook"
        },
        {
            "id": "100086338126407",
            "count": 0,
            "name": "Người dùng facebook"
        },
        {
            "id": "100086411966223",
            "count": 0,
            "name": "Người dùng facebook"
        },
        {
            "id": "100086479540822",
            "count": 0,
            "name": "Người dùng facebook"
        },
        {
            "id": "100086537319292",
            "count": 0,
            "name": "Người dùng facebook"
        },
        {
            "id": "100086608024718",
            "count": 0,
            "name": "Người dùng facebook"
        },
        {
            "id": "100087177684780",
            "count": 0,
            "name": "Người dùng facebook"
        },
        {
            "id": "100087223032350",
            "count": 0,
            "name": "Người dùng facebook"
        },
        {
            "id": "100087241632583",
            "count": 0,
            "name": "Người dùng facebook"
        },
        {
            "id": "100087403423132",
            "count": 0,
            "name": "Người dùng facebook"
        },
        {
            "id": "100087444015436",
            "count": 0,
            "name": "Người dùng facebook"
        },
        {
            "id": "100087446109575",
            "count": 0,
            "name": "Người dùng facebook"
        },
        {
            "id": "100087451973736",
            "count": 0,
            "name": "Người dùng facebook"
        },
        {
            "id": "100087452826273",
            "count": 0,
            "name": "Người dùng facebook"
        },
        {
            "id": "100087581193427",
            "count": 0,
            "name": "Người dùng facebook"
        },
        {
            "id": "100087661293189",
            "count": 0,
            "name": "Người dùng facebook"
        },
        {
            "id": "100087708564424",
            "count": 0,
            "name": "Người dùng facebook"
        },
        {
            "id": "100087728212545",
            "count": 0,
            "name": "Người dùng facebook"
        },
        {
            "id": "100087735655975",
            "count": 0,
            "name": "Người dùng facebook"
        },
        {
            "id": "100087788967099",
            "count": 0,
            "name": "Người dùng facebook"
        },
        {
            "id": "100088009904591",
            "count": 0,
            "name": "Người dùng facebook"
        },
        {
            "id": "100088080985247",
            "count": 0,
            "name": "Người dùng facebook"
        },
        {
            "id": "100088239654137",
            "count": 0,
            "name": "Người dùng facebook"
        },
        {
            "id": "100088304013841",
            "count": 0,
            "name": "Người dùng facebook"
        },
        {
            "id": "100088371745793",
            "count": 0,
            "name": "Người dùng facebook"
        },
        {
            "id": "100088396034616",
            "count": 0,
            "name": "Người dùng facebook"
        },
        {
            "id": "100088426704778",
            "count": 0,
            "name": "Người dùng facebook"
        },
        {
            "id": "100088454352569",
            "count": 0,
            "name": "Người dùng facebook"
        },
        {
            "id": "100088727191960",
            "count": 0,
            "name": "Người dùng facebook"
        },
        {
            "id": "100088736285141",
            "count": 0,
            "name": "Người dùng facebook"
        },
        {
            "id": "100088879443469",
            "count": 0,
            "name": "Người dùng facebook"
        },
        {
            "id": "100089006970460",
            "count": 0,
            "name": "Người dùng facebook"
        },
        {
            "id": "100089021537065",
            "count": 0,
            "name": "Người dùng facebook"
        },
        {
            "id": "100089037437822",
            "count": 0,
            "name": "Người dùng facebook"
        },
        {
            "id": "100089078937363",
            "count": 0,
            "name": "Người dùng facebook"
        },
        {
            "id": "100089135401934",
            "count": 0,
            "name": "Người dùng facebook"
        },
        {
            "id": "100089270354928",
            "count": 0,
            "name": "Người dùng facebook"
        },
        {
            "id": "100089311044327",
            "count": 0,
            "name": "Người dùng facebook"
        },
        {
            "id": "100089319577789",
            "count": 0,
            "name": "Người dùng facebook"
        },
        {
            "id": "100089594261658",
            "count": 0,
            "name": "Người dùng facebook"
        },
        {
            "id": "100089597169878",
            "count": 0,
            "name": "Người dùng facebook"
        },
        {
            "id": "100089608287247",
            "count": 0,
            "name": "Người dùng facebook"
        },
        {
            "id": "100089615088261",
            "count": 0,
            "name": "Người dùng facebook"
        },
        {
            "id": "100089752437202",
            "count": 0,
            "name": "Người dùng facebook"
        },
        {
            "id": "100089854377008",
            "count": 0,
            "name": "Người dùng facebook"
        },
        {
            "id": "100089892835963",
            "count": 0,
            "name": "Người dùng facebook"
        },
        {
            "id": "100089914403718",
            "count": 0,
            "name": "Người dùng facebook"
        },
        {
            "id": "100089918617197",
            "count": 0,
            "name": "Người dùng facebook"
        },
        {
            "id": "100089933977196",
            "count": 0,
            "name": "Người dùng facebook"
        },
        {
            "id": "100089948816816",
            "count": 0,
            "name": "Người dùng facebook"
        },
        {
            "id": "100090047276847",
            "count": 0,
            "name": "Người dùng facebook"
        },
        {
            "id": "100090075093924",
            "count": 0,
            "name": "Người dùng facebook"
        },
        {
            "id": "100090204715224",
            "count": 0,
            "name": "Người dùng facebook"
        },
        {
            "id": "100090206681674",
            "count": 0,
            "name": "Người dùng facebook"
        },
        {
            "id": "100090232310769",
            "count": 0,
            "name": "Người dùng facebook"
        },
        {
            "id": "100090287706395",
            "count": 0,
            "name": "Người dùng facebook"
        },
        {
            "id": "100090349088487",
            "count": 0,
            "name": "Người dùng facebook"
        },
        {
            "id": "100090480626218",
            "count": 0,
            "name": "Người dùng facebook"
        },
        {
            "id": "100090487747838",
            "count": 0,
            "name": "Người dùng facebook"
        },
        {
            "id": "100090573266947",
            "count": 0,
            "name": "Người dùng facebook"
        },
        {
            "id": "100090586627799",
            "count": 0,
            "name": "Người dùng facebook"
        },
        {
            "id": "100090667071803",
            "count": 0,
            "name": "Người dùng facebook"
        },
        {
            "id": "100090892813611",
            "count": 0,
            "name": "Người dùng facebook"
        },
        {
            "id": "100090931960391",
            "count": 0,
            "name": "Người dùng facebook"
        },
        {
            "id": "100091169177735",
            "count": 0,
            "name": "Người dùng facebook"
        },
        {
            "id": "100091242102045",
            "count": 0,
            "name": "Người dùng facebook"
        },
        {
            "id": "100091356849300",
            "count": 0,
            "name": "Người dùng facebook"
        },
        {
            "id": "100091364680112",
            "count": 0,
            "name": "Người dùng facebook"
        },
        {
            "id": "100091370330916",
            "count": 0,
            "name": "Người dùng facebook"
        },
        {
            "id": "100091393628777",
            "count": 0,
            "name": "Người dùng facebook"
        },
        {
            "id": "100091438323320",
            "count": 0,
            "name": "Người dùng facebook"
        },
        {
            "id": "100091472761117",
            "count": 0,
            "name": "Người dùng facebook"
        },
        {
            "id": "100091487242291",
            "count": 0,
            "name": "Người dùng facebook"
        },
        {
            "id": "100091694487260",
            "count": 0,
            "name": "Người dùng facebook"
        },
        {
            "id": "100092212964221",
            "count": 0,
            "name": "Người dùng facebook"
        },
        {
            "id": "100092213439559",
            "count": 0,
            "name": "Người dùng facebook"
        },
        {
            "id": "100092401010035",
            "count": 0,
            "name": "Người dùng facebook"
        },
        {
            "id": "100092729792306",
            "count": 0,
            "name": "Người dùng facebook"
        }
    ],
    "time": 2
}